CoreConsultingWings
djangoDeployGitHook
mkt4bIntegratorSendingblue
